LICENSE
README.md
setup.py
mythicinfinity/__init__.py
mythicinfinity/__version__.py
mythicinfinity/client.py
mythicinfinity/streaming_tts_client.py
mythicinfinity.egg-info/PKG-INFO
mythicinfinity.egg-info/SOURCES.txt
mythicinfinity.egg-info/dependency_links.txt
mythicinfinity.egg-info/not-zip-safe
mythicinfinity.egg-info/requires.txt
mythicinfinity.egg-info/top_level.txt
mythicinfinity/gen/__init__.py
mythicinfinity/gen/base_client.py
mythicinfinity/gen/environment.py
mythicinfinity/gen/core/__init__.py
mythicinfinity/gen/core/api_error.py
mythicinfinity/gen/core/client_wrapper.py
mythicinfinity/gen/core/datetime_utils.py
mythicinfinity/gen/core/file.py
mythicinfinity/gen/core/http_client.py
mythicinfinity/gen/core/jsonable_encoder.py
mythicinfinity/gen/core/pydantic_utilities.py
mythicinfinity/gen/core/query_encoder.py
mythicinfinity/gen/core/remove_none_from_dict.py
mythicinfinity/gen/core/request_options.py
mythicinfinity/gen/core/serialization.py
mythicinfinity/gen/errors/__init__.py
mythicinfinity/gen/errors/unprocessable_entity_error.py
mythicinfinity/gen/tts/__init__.py
mythicinfinity/gen/tts/client.py
mythicinfinity/gen/tts/types/__init__.py
mythicinfinity/gen/tts/types/format.py
mythicinfinity/gen/tts/voices/__init__.py
mythicinfinity/gen/tts/voices/client.py
mythicinfinity/gen/types/__init__.py
mythicinfinity/gen/types/http_validation_error.py
mythicinfinity/gen/types/validation_error.py
mythicinfinity/gen/types/validation_error_loc_item.py
mythicinfinity/gen/types/voice.py
mythicinfinity/gen/types/voice_metadata.py
mythicinfinity/gen/types/voice_options.py
test/test_client.py