Metadata-Version: 2.2
Name: mythicinfinity
Version: 0.1.5
Summary: Mythic Infinity python client library.
Home-page: https://www.mythicinfinity.com/
Author: Mythic Infinity
License: MIT
Project-URL: Repository, https://github.com/mythicinfinity/mythicinfinity-python
Classifier: Intended Audience :: Developers
Classifier: Programming Language :: Python
Classifier: Programming Language :: Python :: 3
Classifier: Programming Language :: Python :: 3.8
Classifier: Programming Language :: Python :: 3.9
Classifier: Programming Language :: Python :: 3.10
Classifier: Programming Language :: Python :: 3.11
Classifier: Programming Language :: Python :: 3.12
Classifier: Operating System :: OS Independent
Classifier: Operating System :: POSIX
Classifier: Operating System :: MacOS
Classifier: Operating System :: POSIX :: Linux
Classifier: Operating System :: Microsoft :: Windows
Classifier: Topic :: Software Development :: Libraries :: Python Modules
Classifier: Typing :: Typed
Classifier: License :: OSI Approved :: MIT License
Requires-Python: >=3.8
License-File: LICENSE
Requires-Dist: httpx>=0.21.2
Requires-Dist: pydantic>=1.9.2
Requires-Dist: pydantic-core==2.*,>=2.18.2
Requires-Dist: typing_extensions>=4.0.0
Provides-Extra: test
Requires-Dist: pytest==8.3.4; extra == "test"
Requires-Dist: pytest-xdist==3.6.1; extra == "test"
Requires-Dist: pytest-asyncio==0.24.0; extra == "test"
Dynamic: author
Dynamic: classifier
Dynamic: description
Dynamic: description-content-type
Dynamic: home-page
Dynamic: license
Dynamic: project-url
Dynamic: provides-extra
Dynamic: requires-dist
Dynamic: requires-python
Dynamic: summary
